akamai_shared_cloudlets/__init__.py
akamai_shared_cloudlets/__main__.py
akamai_shared_cloudlets/akamai_api_requests_abstractions.py
akamai_shared_cloudlets/akamai_enums.py
akamai_shared_cloudlets/akamai_project_constants.py
akamai_shared_cloudlets/exceptions.py
akamai_shared_cloudlets/http_requests.py
akamai_shared_cloudlets/shared.py
akamai_shared_cloudlets-0.1.1.dist-info/LICENSE
akamai_shared_cloudlets-0.1.1.dist-info/METADATA
akamai_shared_cloudlets-0.1.1.dist-info/WHEEL
akamai_shared_cloudlets-0.1.1.dist-info/RECORD
