Metadata-Version: 2.1
Name: akamai-shared-cloudlets
Version: 0.1.1
Summary: Library that implements Akamai PI requests to control cloudlet API version 3
Author: TomasHampl
Author-email: tomas.hampl@gmail.com
Requires-Python: >3.10
Classifier: Programming Language :: Python :: 3
Classifier: Programming Language :: Python :: 3.11
Classifier: Programming Language :: Python :: 3.12
Requires-Dist: click (>=8.1.7,<9.0.0)
Requires-Dist: edgegrid-python (>=1.3.1,<2.0.0)
Requires-Dist: ndg-httpsclient (>=0.5.1,<0.6.0)
Requires-Dist: pyOpenSSL (>=23.3.0,<24.0.0)
Requires-Dist: requests (>=2.31.0,<3.0.0)
